{
    "id": 60,
    "date": "2023-04-22T20:29:32",
    "date_gmt": "2023-04-22T20:29:32",
    "guid": {
        "rendered": "http://localhost/wp-content/uploads/2023/04/seat-auto-34.jpg"
    },
    "modified": "2023-04-22T20:29:32",
    "modified_gmt": "2023-04-22T20:29:32",
    "slug": "seat-auto-34",
    "status": "inherit",
    "type": "attachment",
    "link": "http://localhost/seat-auto-34/",
    "title": {
        "rendered": "seat-auto-34"
    },
    "author": 3,
    "comment_status": "open",
    "ping_status": "closed",
    "template": "",
    "meta": [],
    "description": {
        "rendered": "<p class=\"attachment\"><a href='http://localhost/wp-content/uploads/2023/04/seat-auto-34.jpg'><img width=\"300\" height=\"149\" src=\"http://localhost/wp-content/uploads/2023/04/seat-auto-34-300x149.jpg\" class=\"attachment-medium size-medium\" alt=\"\" decoding=\"async\" loading=\"lazy\" srcset=\"http://localhost/wp-content/uploads/2023/04/seat-auto-34-300x149.jpg 300w, http://localhost/wp-content/uploads/2023/04/seat-auto-34-768x382.jpg 768w, http://localhost/wp-content/uploads/2023/04/seat-auto-34.jpg 820w\" sizes=\"(max-width: 300px) 100vw, 300px\" /></a></p>\n"
    },
    "caption": {
        "rendered": ""
    },
    "alt_text": "",
    "media_type": "image",
    "mime_type": "image/jpeg",
    "media_details": {
        "width": 820,
        "height": 408,
        "file": "2023/04/seat-auto-34.jpg",
        "filesize": 163143,
        "sizes": {
            "medium": {
                "file": "seat-auto-34-300x149.jpg",
                "width": 300,
                "height": 149,
                "filesize": 9331,
                "mime_type": "image/jpeg",
                "source_url": "http://localhost/wp-content/uploads/2023/04/seat-auto-34-300x149.jpg"
            },
            "thumbnail": {
                "file": "seat-auto-34-150x150.jpg",
                "width": 150,
                "height": 150,
                "filesize": 5356,
                "mime_type": "image/jpeg",
                "source_url": "http://localhost/wp-content/uploads/2023/04/seat-auto-34-150x150.jpg"
            },
            "medium_large": {
                "file": "seat-auto-34-768x382.jpg",
                "width": 768,
                "height": 382,
                "filesize": 37040,
                "mime_type": "image/jpeg",
                "source_url": "http://localhost/wp-content/uploads/2023/04/seat-auto-34-768x382.jpg"
            },
            "full": {
                "file": "seat-auto-34.jpg",
                "width": 820,
                "height": 408,
                "mime_type": "image/jpeg",
                "source_url": "http://localhost/wp-content/uploads/2023/04/seat-auto-34.jpg"
            }
        },
        "image_meta": {
            "aperture": "0",
            "credit": "",
            "camera": "",
            "caption": "",
            "created_timestamp": "0",
            "copyright": "",
            "focal_length": "0",
            "iso": "0",
            "shutter_speed": "0",
            "title": "",
            "orientation": "0",
            "keywords": []
        }
    },
    "post": null,
    "source_url": "http://localhost/wp-content/uploads/2023/04/seat-auto-34.jpg",
    "_links": {
        "self": [
            {
                "href": "http://localhost/wp-json/wp/v2/media/60"
            }
        ],
        "collection": [
            {
                "href": "http://localhost/wp-json/wp/v2/media"
            }
        ],
        "about": [
            {
                "href": "http://localhost/wp-json/wp/v2/types/attachment"
            }
        ],
        "author": [
            {
                "embeddable": true,
                "href": "http://localhost/wp-json/wp/v2/users/3"
            }
        ],
        "replies": [
            {
                "embeddable": true,
                "href": "http://localhost/wp-json/wp/v2/comments?post=60"
            }
        ]
    }
}
